{
    "id": 108690946,
    "name": "FunHouse",
    "author": "Mylam999",
    "creators": ["Mylam999"],
    "verifier": "Mylam999",
    "verification": "https://youtu.be/Dt6d6YQUfhA?si=wQveDZWmtPND26p-",
    "percentToQualify": 100,
    "password": "free",
    "records": [
        {
            "user": "allu",
            "hz": 60,
            "percent": 100
        },
        {
            "user": "SadCraft0o",
            "hz": 60,
            "percent": 100
        },
        {
            "user": "Farlayy",
            "hz": 240,
            "percent": 100
        },
        {
            "user": "Miksutic",
            "video": "https://youtu.be/qUIbJqa0IDg",
            "hz": 360,
            "percent": 100
        },
        {
            "user": "Slashy",
            "hz": 60,
            "percent": 100
        },
        {
            "user": "Frostytoes",
            "hz": 60,
            "percent": 100
        },
        {
            "user": "Monkey",
            "hz": 240,
            "percent": 100
        },
        {
            "user": "Spunstep",
            "hz": 500,
            "percent": 100
        },
        {
            "user": "EndGrain",
            "hz": 144,
            "percent": 100
        },
        {
            "user": "EABH",
            "hz": 240,
            "percent": 100
        }
    ]
}
