{
    "id": 106764806,
    "name": "No",
    "author": "RIKINITY",
    "creators": ["RIKINITY"],
    "verifier": "RIKINITY",
    "verification": "https://youtu.be/qrxUJtxH6P4",
    "percentToQualify": 100,
    "password": "free",
    "records": [
        {
            "user": "NatNat",
            "hz": 288,
            "percent": 100
        },
        {
            "user": "naqte",
            "hz": 144,
            "percent": 100
        },
        {
            "user": "SadCraft0o",
            "hz": 60,
            "percent": 100
        },
        {
            "user": "Voiddle",
            "hz": 144,
            "percent": 100
        },
        {
            "user": "KrisYa",
            "video": "https://www.youtube.com/watch?v=DOqMblbvE_g",
            "hz": 360,
            "percent": 100
        },
        {
            "user": "SH4IN3",
            "video": "https://medal.tv/games/geometry-dash/clips/ii3rZ4fREvA8ARbF-/d1337J4dCj3n?invite=cr-MSxGazQsMjA0NjczODMyLA",
            "hz": 360,
            "percent": 100
        }
    ]
}
